pyromb/__init__.py
pyromb/core/__init__.py
pyromb/core/catchment.py
pyromb/core/model.py
pyromb/core/traveller.py
pyromb/core/attributes/__init__.py
pyromb/core/attributes/basin.py
pyromb/core/attributes/confluence.py
pyromb/core/attributes/node.py
pyromb/core/attributes/reach.py
pyromb/core/geometry/__init__.py
pyromb/core/geometry/line.py
pyromb/core/geometry/point.py
pyromb/core/geometry/polygon.py
pyromb/core/gis/__init__.py
pyromb/core/gis/builder.py
pyromb/core/gis/vector_layer.py
pyromb/math/__init__.py
pyromb/math/geometry.py
pyromb/models/__init__.py
pyromb/models/rorb.py
pyromb/models/urbs.py
pyromb/models/wbnm.py
pyromb/reporting/__init__.py
pyromb/reporting/rorb.py
pyromb/resources/__init__.py
pyromb/resources/formatting.json
pyromb/resources/rorb.py
pyromb/utils/__init__.py
pyromb-0.3.0.dist-info/METADATA
pyromb-0.3.0.dist-info/WHEEL
pyromb-0.3.0.dist-info/licenses/LICENSE
pyromb-0.3.0.dist-info/RECORD
