Metadata-Version: 2.4
Name: pyromb
Version: 0.3.0
Summary: Runoff Model Builder (Pyromb) is a package used for building RORB, WBNM, and URBS control files from catchment diagrams built from ESRI shapefiles. Its primary use is in the QGIS plugins 'Runoff Model Builder', though can be used as a standalone Python library
Project-URL: Homepage, https://github.com/norman-tom/pyromb
Project-URL: Bug Tracker, https://github.com/norman-tom/pyromb/issues
Author-email: Tom Norman <tom@ncos.com.au>
License-File: LICENSE
Classifier: License :: OSI Approved :: MIT License
Classifier: Operating System :: OS Independent
Classifier: Programming Language :: Python :: 3
Requires-Python: >=3.12
Requires-Dist: matplotlib
Requires-Dist: numpy
Requires-Dist: pandas
